Metadata-Version: 2.1
Name: xors
Version: 0.0.0
Summary: Abstractable XOR-based threshold secret sharing implementation in pure-Python.
Author: Wyatt Howe
Author-email: wyatt@nthparty.com
License: MIT
Project-URL: Repository, https://github.com/nthparty/xors
Project-URL: Documentation, https://xors.readthedocs.io
Requires-Python: >=3.7
Provides-Extra: docs
Provides-Extra: test
Provides-Extra: lint
Provides-Extra: coveralls
Provides-Extra: publish
License-File: LICENSE
